adv_lion/__init__.py
adv_lion/optim/DAdapt_Lion.py
adv_lion/optim/Lion.py
adv_lion/optim/__init__.py
adv_lion/util/OrthoGrad.py
adv_lion/util/__init__.py
adv_lion/util/bf16_stochastic_rounding.py
adv_lion-0.1.1.dist-info/licenses/LICENSE
adv_lion-0.1.1.dist-info/METADATA
adv_lion-0.1.1.dist-info/WHEEL
adv_lion-0.1.1.dist-info/top_level.txt
adv_lion-0.1.1.dist-info/RECORD
